{
 "actions": [],
 "allow_rename": 1,
 "creation": "2023-03-23 01:42:46.955719",
 "doctype": "DocType",
 "editable_grid": 1,
 "engine": "InnoDB",
 "field_order": [
  "service_features_name"
 ],
 "fields": [
  {
   "fieldname": "service_features_name",
   "fieldtype": "Small Text",
   "in_list_view": 1,
   "label": "Service Features Name",
   "translatable": 1
  }
 ],
 "index_web_pages_for_search": 1,
 "istable": 1,
 "links": [],
 "modified": "2023-03-23 02:09:03.817149",
 "modified_by": "Administrator",
 "module": "Space Secure",
 "name": "Service Features",
 "owner": "Administrator",
 "permissions": [],
 "sort_field": "modified",
 "sort_order": "DESC"
}